<gallery>
  <pic>
      <lores>Large-de-vue-1</lores>
      <title>exhibition view 1, Kiasma, Helsinki 2007</title>
      <dimensions></dimensions>
      <year></year>
      <edition></edition>
    </pic>
    <pic>
      <lores>Large-de-vue-2</lores>
      <title>exhibition view 2, Kiasma, Helsinki 2007</title>
      <dimensions></dimensions>
      <year></year>
      <edition></edition>
    </pic>
    <pic>
      <lores>Assez-lent</lores>
      <title>Assez lent</title>
      <dimensions></dimensions>
      <year></year>
      <edition></edition>
    </pic>
    <pic>
      <lores>tres-lie-et-melancholiqu</lores>
      <title>très lié et mélancholique</title>
      <dimensions></dimensions>
      <year></year>
      <edition></edition>
    </pic>
    <pic>
      <lores>Voyez</lores>
      <title>Voyez</title>
      <dimensions></dimensions>
      <year></year>
      <edition></edition>
    </pic>
    <pic>
      <lores>leger-mais-fort</lores>
      <title>léger mais fort</title>
      <dimensions></dimensions>
      <year></year>
      <edition></edition>
    </pic>
    <pic>
      <lores>ralentir</lores>
      <title>ralentir</title>
      <dimensions></dimensions>
      <year></year>
      <edition></edition>
    </pic>
    <pic>
      <lores>Reprendre</lores>
      <title>Reprendre</title>
      <dimensions></dimensions>
      <year></year>
      <edition></edition>
    </pic>
    <pic>
      <lores>tres-lie</lores>
      <title>très lié</title>
      <dimensions></dimensions>
      <year></year>
      <edition></edition>
    </pic>
    <pic>
      <lores>Grossir</lores>
      <title>Grossir</title>
      <dimensions></dimensions>
      <year></year>
      <edition></edition>
    </pic>
    <pic>
      <lores>Particulierement</lores>
      <title>Particulièrement</title>
      <dimensions></dimensions>
      <year></year>
      <edition></edition>
    </pic>
    <pic>
      <lores>retenez,-je-vous-prie</lores>
      <title>retenez, je vous prie</title>
      <dimensions></dimensions>
      <year></year>
      <edition></edition>
    </pic>
    <pic>
      <lores>11-Plus-lent</lores>
      <title>Plus lent</title>
      <dimensions></dimensions>
      <year></year>
      <edition></edition>
    </pic>
    <pic>
      <lores>en-dehors</lores>
      <title>en dehors</title>
      <dimensions></dimensions>
      <year></year>
      <edition></edition>
    </pic>
    <pic>
      <lores>ralentir</lores>
      <title>ralentir</title>
      <dimensions></dimensions>
      <year></year>
      <edition></edition>
    </pic>
    <pic>
      <lores>Large-de-vue</lores>
      <title>Large de vue</title>
      <dimensions></dimensions>
      <year></year>
      <edition></edition>
    </pic>
    <pic>
      <lores>Ne-tournez-pas</lores>
      <title>Ne tournez pas</title>
      <dimensions></dimensions>
      <year></year>
      <edition></edition>
    </pic>
    <pic>
      <lores>tres-chante</lores>
      <title>très chanté</title>
      <dimensions></dimensions>
      <year></year>
      <edition></edition>
    </pic>
    <pic>
      <lores>Positivement</lores>
      <title>Positivement</title>
      <dimensions></dimensions>
      <year></year>
      <edition></edition>
    </pic>
    <pic>
      <lores>Mieux</lores>
      <title>Mieux</title>
      <dimensions></dimensions>
      <year></year>
      <edition></edition>
    </pic>
    <pic>
      <lores>Encore</lores>
      <title>Encore</title>
      <dimensions></dimensions>
      <year></year>
      <edition></edition>
    </pic>
    <pic>
      <lores>Grattez</lores>
      <title>Grattez</title>
      <dimensions></dimensions>
      <year></year>
      <edition></edition>
    </pic>
    <pic>
      <lores>Non-vite</lores>
      <title>Non vite</title>
      <dimensions></dimensions>
      <year></year>
      <edition></edition>
    </pic>
    <pic>
      <lores>Souriez</lores>
      <title>Souriez</title>
      <dimensions></dimensions>
      <year></year>
      <edition></edition>
    </pic>
    <pic>
      <lores>Avec-plaisir</lores>
      <title>Avec plaisir</title>
      <dimensions></dimensions>
      <year></year>
      <edition></edition>
    </pic>
    <pic>
      <lores>Naturellement</lores>
      <title>Naturellement</title>
      <dimensions></dimensions>
      <year></year>
      <edition></edition>
    </pic>
    <pic>
      <lores>Depuis</lores>
      <title>Depuis</title>
      <dimensions></dimensions>
      <year></year>
      <edition></edition>
    </pic>
    <pic>
      <lores>en-dehors</lores>
      <title>en dehors</title>
      <dimensions></dimensions>
      <year></year>
      <edition></edition>
    </pic>
    <pic>
      <lores>sans-mechancete</lores>
      <title>sans méchanceté</title>
      <dimensions></dimensions>
      <year></year>
      <edition></edition>
    </pic>
    <pic>
      <lores>Droit</lores>
      <title>Droit</title>
      <dimensions></dimensions>
      <year></year>
      <edition></edition>
    </pic>
    <pic>
      <lores>Visible</lores>
      <title>Visible</title>
      <dimensions></dimensions>
      <year></year>
      <edition></edition>
    </pic>
    <pic>
      <lores>De-coin</lores>
      <title>De coin</title>
      <dimensions></dimensions>
      <year></year>
      <edition></edition>
    </pic>
    <pic>
      <lores>Prenez</lores>
      <title>Prenez</title>
      <dimensions></dimensions>
      <year></year>
      <edition></edition>
    </pic>
    <pic>
      <lores>chanter</lores>
      <title>chanter</title>
      <dimensions></dimensions>
      <year></year>
      <edition></edition>
    </pic>
    <pic>
      <lores>Necessairement</lores>
      <title>Nécessairement</title>
      <dimensions></dimensions>
      <year></year>
      <edition></edition>
    </pic>
    <pic>
      <lores>Beaucoup</lores>
      <title>Beaucoup</title>
      <dimensions></dimensions>
      <year></year>
      <edition></edition>
    </pic>
    <pic>
      <lores>A-voir</lores>
      <title>A voir</title>
      <dimensions></dimensions>
      <year></year>
      <edition></edition>
    </pic>
    <pic>
      <lores>Ne-parlez-pas</lores>
      <title>Ne parlez pas</title>
      <dimensions></dimensions>
      <year></year>
      <edition></edition>
    </pic>
    <pic>
      <lores>Dire</lores>
      <title>Dire</title>
      <dimensions></dimensions>
      <year></year>
      <edition></edition>
    </pic>
    <pic>
      <lores>Precieux</lores>
      <title>Précieux</title>
      <dimensions></dimensions>
      <year></year>
      <edition></edition>
    </pic>
    <pic>
      <lores>crescendo</lores>
      <title>crescendo</title>
      <dimensions></dimensions>
      <year></year>
      <edition></edition>
    </pic>
    <pic>
      <lores>Regardez</lores>
      <title>Regardez</title>
      <dimensions></dimensions>
      <year></year>
      <edition></edition>
    </pic>
    <pic>
      <lores>Seul</lores>
      <title>Seul</title>
      <dimensions></dimensions>
      <year></year>
      <edition></edition>
    </pic>
    <pic>
      <lores>En-face</lores>
      <title>En face</title>
      <dimensions></dimensions>
      <year></year>
      <edition></edition>
    </pic>
    <pic>
      <lores>Veritable</lores>
      <title>Véritable</title>
      <dimensions></dimensions>
      <year></year>
      <edition></edition>
    </pic>
    <pic>
      <lores>retenir</lores>
      <title>retenir</title>
      <dimensions></dimensions>
      <year></year>
      <edition></edition>
    </pic>
    <pic>
      <lores>noblement</lores>
      <title>noblement</title>
      <dimensions></dimensions>
      <year></year>
      <edition></edition>
    </pic>
  </gallery>